.codecov.yml
.coveragerc
.csslintrc
.flake8
.gitattributes
.gitignore
.jshintignore
.markdownlintrc
AUTHORS
CONTRIBUTING.rst
LICENSE
MANIFEST.in
Makefile
README.md
appveyor.yml
readthedocs.yml
requirements.txt
setup.cfg
setup.py
tox.ini
bin/biovis-report
biovis_report/__init__.py
biovis_report/__main__.py
biovis_report/exceptions.py
biovis_report/exit_code.py
biovis_report/json_checker.py
biovis_report/plugin_utils.py
biovis_report/report_mgmt.py
biovis_report/utils.py
biovis_report/version.py
biovis_report.egg-info/PKG-INFO
biovis_report.egg-info/SOURCES.txt
biovis_report.egg-info/dependency_links.txt
biovis_report.egg-info/entry_points.txt
biovis_report.egg-info/not-zip-safe
biovis_report.egg-info/requires.txt
biovis_report.egg-info/top_level.txt
biovis_report/config/__init__.py
biovis_report/config/config.py
biovis_report/config/schema.py
biovis_report/config/schemas/config_plugin.json
biovis_report/config/schemas/config_report.json
biovis_report/resources/defaults.template
biovis_report/resources/mkdocs.yml.template
conda.recipe/bld.bat
conda.recipe/build.sh
conda.recipe/conda_build_config.yaml
conda.recipe/meta.yaml
docs/CNAME
docs/index.md
docs/about/contributing.md
docs/about/license.md
docs/about/release-notes.md
docs/css/extra.css
docs/img/initial-layout.png
docs/img/mkdocs.png
docs/img/multipage.png
docs/img/readthedocs.png
docs/img/screenshot.png
docs/img/search.png
docs/img/site-name.png
docs/img/win-py-install.png
docs/user-guide/configuration.md
docs/user-guide/custom-themes.md
docs/user-guide/deploying-your-docs.md
docs/user-guide/plugins.md
docs/user-guide/styling-your-docs.md
docs/user-guide/writing-your-docs.md
mkdocs/__init__.py
mkdocs/__main__.py
mkdocs/exceptions.py
mkdocs/plugins.py
mkdocs/theme.py
mkdocs/commands/__init__.py
mkdocs/commands/build.py
mkdocs/commands/gh_deploy.py
mkdocs/commands/new.py
mkdocs/commands/serve.py
mkdocs/config/__init__.py
mkdocs/config/base.py
mkdocs/config/config_options.py
mkdocs/config/defaults.py
mkdocs/contrib/__init__.py
mkdocs/contrib/header_injector/__init__.py
mkdocs/contrib/search/__init__.py
mkdocs/contrib/search/prebuild-index.js
mkdocs/contrib/search/search_index.py
mkdocs/contrib/search/lunr-language/lunr.da.js
